reverbed/__init__.py
reverbed/audio.py
reverbed/cli.py
reverbed/core.py
reverbed/search.py
reverbed/utils.py
reverbed/video.py
reverbed-0.2.0.dist-info/METADATA
reverbed-0.2.0.dist-info/WHEEL
reverbed-0.2.0.dist-info/entry_points.txt
reverbed-0.2.0.dist-info/top_level.txt
reverbed-0.2.0.dist-info/RECORD
