Metadata-Version: 2.4
Name: reverbed
Version: 0.2.0
Summary: A Python package for creating slowed and reverbed versions of videos
Home-page: https://github.com/paramp07/reverbed
Author: Param
Author-email: patelparam0767@gmail.com
Classifier: Programming Language :: Python :: 3
Classifier: License :: OSI Approved :: MIT License
Classifier: Operating System :: OS Independent
Requires-Python: >=3.6
Requires-Dist: pytube
Requires-Dist: moviepy
Requires-Dist: yt-dlp
Requires-Dist: soundfile
Requires-Dist: pedalboard
Requires-Dist: numpy
Provides-Extra: dev
Requires-Dist: pytest; extra == "dev"
Requires-Dist: black; extra == "dev"
Requires-Dist: flake8; extra == "dev"
Requires-Dist: build; extra == "dev"
Requires-Dist: twine; extra == "dev"
Provides-Extra: api
Requires-Dist: fastapi; extra == "api"
Requires-Dist: uvicorn; extra == "api"
Requires-Dist: pydantic; extra == "api"
Dynamic: author
Dynamic: author-email
Dynamic: classifier
Dynamic: description
Dynamic: description-content-type
Dynamic: home-page
Dynamic: provides-extra
Dynamic: requires-dist
Dynamic: requires-python
Dynamic: summary
